akenoai/__init__.py
akenoai/__version__.py
akenoai/akeno.py
akenoai/api_decorator.py
akenoai/errors.py
akenoai/logger.py
akenoai/openai.py
akenoai/pyro_decorator.py
akenoai/reqs.py
akenoai/xnxx.py
akenoai/api_random/__init__.py
akenoai/api_random/chatgpt.py
akenoai/base/__init__.py
akenoai/clients/__init__.py
akenoai/clients/enums.py
akenoai/custom/__init__.py
akenoai/database/__init__.py
akenoai/database/types.py
akenoai/dev/__init__.py
akenoai/enums/__init__.py
akenoai/enums/_chat.py
akenoai/enums/auto_name.py
akenoai/inline/__init__.py
akenoai/inline/inline_query.py
akenoai/manager/__init__.py
akenoai/middleware/__init__.py
akenoai/middleware/cors.py
akenoai/models/__init__.py
akenoai/runner/__init__.py
akenoai/streamlit/__init__.py
akenoai/types/__init__.py
akenoai-2.0.1.dist-info/licenses/LICENSE
akenoai-2.0.1.dist-info/METADATA
akenoai-2.0.1.dist-info/WHEEL
akenoai-2.0.1.dist-info/top_level.txt
akenoai-2.0.1.dist-info/RECORD
